meteocat/__init__.py
meteocat/condition.py
meteocat/config_flow.py
meteocat/const.py
meteocat/coordinator.py
meteocat/entity.py
meteocat/helpers.py
meteocat/manifest.json
meteocat/options_flow.py
meteocat/sensor.py
meteocat/strings.json
meteocat/translations/ca.json
meteocat/translations/en.json
meteocat/translations/es.json
meteocat/version.py
meteocat-0.1.17.dist-info/AUTHORS.md
meteocat-0.1.17.dist-info/LICENSE
meteocat-0.1.17.dist-info/METADATA
meteocat-0.1.17.dist-info/WHEEL
meteocat-0.1.17.dist-info/RECORD
