Metadata-Version: 2.1
Name: meteocat
Version: 0.1.17
Summary: Script para obtener datos meteorológicos de la API de Meteocat
Home-page: https://gitlab.com/figorr/meteocat
License: Apache-2.0
Keywords: meteocat
Author: figorr
Author-email: jdcuartero@yahoo.es
Requires-Python: ==3.12.7
Classifier: License :: OSI Approved :: Apache Software License
Classifier: Programming Language :: Python :: 3
Requires-Dist: aiofiles (>=24.1.0,<25.0.0)
Requires-Dist: python-dotenv (>=1.0.1,<2.0.0)
Requires-Dist: python-semantic-release (>=9.14.0,<10.0.0)
Requires-Dist: requests (>=2.32.3,<3.0.0)
Requires-Dist: setuptools (>=75.5.0,<76.0.0)
Requires-Dist: simplejson (>=3.19.3,<4.0.0)
Requires-Dist: twine (>=5.1.1,<6.0.0)
Requires-Dist: voluptuous (>=0.15.2,<0.16.0)
Project-URL: Repository, https://gitlab.com/figorr/meteocat
